lobster/__init__.py
lobster/common/__init__.py
lobster/common/errors.py
lobster/common/exceptions.py
lobster/common/file_collector.py
lobster/common/file_tag_generator.py
lobster/common/io.py
lobster/common/items.py
lobster/common/level_definition.py
lobster/common/lexer.py
lobster/common/location.py
lobster/common/meta_data_tool_base.py
lobster/common/multi_file_input_config.py
lobster/common/multi_file_input_tool.py
lobster/common/parser.py
lobster/common/report.py
lobster/common/tool.py
lobster/common/version.py
lobster/htmldoc/__init__.py
lobster/htmldoc/assets.py
lobster/htmldoc/htmldoc.py
lobster/tools/core/ci_report/__init__.py
lobster/tools/core/ci_report/ci_report.py
lobster/tools/core/html_report/__init__.py
lobster/tools/core/html_report/html_report.py
lobster/tools/core/html_report/html_report_css.py
lobster/tools/core/html_report/html_report_js.py
lobster/tools/core/online_report/__init__.py
lobster/tools/core/online_report/online_report.py
lobster/tools/core/online_report/path_to_url_converter.py
lobster/tools/core/online_report_nogit/__init__.py
lobster/tools/core/online_report_nogit/online_report_nogit.py
lobster/tools/core/report/__init__.py
lobster/tools/core/report/report.py
bmw_lobster_core-1.0.2.dist-info/METADATA
bmw_lobster_core-1.0.2.dist-info/WHEEL
bmw_lobster_core-1.0.2.dist-info/entry_points.txt
bmw_lobster_core-1.0.2.dist-info/top_level.txt
bmw_lobster_core-1.0.2.dist-info/RECORD
